dump_psql_roles_grants/__main__.py
dump_psql_roles_grants/__version__.py
dump_psql_roles_grants/classes.py
dump_psql_roles_grants/cli.py
dump_psql_roles_grants/commands.py
dump_psql_roles_grants/config.py
dump_psql_roles_grants/get_data.py
dump_psql_roles_grants/table.py
dump_psql_roles_grants-0.3.1.dist-info/METADATA
dump_psql_roles_grants-0.3.1.dist-info/WHEEL
dump_psql_roles_grants-0.3.1.dist-info/entry_points.txt
dump_psql_roles_grants-0.3.1.dist-info/RECORD
