Metadata-Version: 2.1
Name: dump-psql-roles-grants
Version: 0.3.1
Summary: Dump Postgres Roles and Grants
Home-page: https://github.com/rgeraskin/dump_psql_roles_grants
License: MIT
Keywords: postgres,psql,roles,grants,dump
Author: Roman Geraskin
Author-email: roman.n.geraskin@gmail.com
Requires-Python: >=3.12,<4.0
Classifier: License :: OSI Approved :: MIT License
Classifier: Programming Language :: Python :: 3
Classifier: Programming Language :: Python :: 3.12
Provides-Extra: binary
Requires-Dist: PyYAML (>=6.0.1,<7.0.0)
Requires-Dist: click (>=8.1.7,<9.0.0)
Requires-Dist: icecream (>=2.1.3,<3.0.0)
Requires-Dist: psycopg (>=3.1.18,<4.0.0)
Requires-Dist: psycopg-binary (>=3.1.18,<4.0.0) ; extra == "binary"
Requires-Dist: psycopg-infdate (>=1.0.3,<2.0.0)
Requires-Dist: pytablewriter (>=1.2.0,<2.0.0)
Requires-Dist: rich (>=13.7.1,<14.0.0)
Project-URL: Repository, https://github.com/rgeraskin/dump_psql_roles_grants
